{"nodes": [{"id": "c_users_diego_ramirez_j_rnwconstructionsite_agents_skills_vercel_optimize_lib_scanners_unoptimized_image_mjs", "label": "unoptimized-image.mjs", "file_type": "code", "source_file": "C:\\Users\\Diego Ramirez\\J-RNWConstructionSite\\.agents\\skills\\vercel-optimize\\lib\\scanners\\unoptimized-image.mjs", "source_location": "L1"}, {"id": "scanners_unoptimized_image_metadata", "label": "metadata", "file_type": "code", "source_file": "C:\\Users\\Diego Ramirez\\J-RNWConstructionSite\\.agents\\skills\\vercel-optimize\\lib\\scanners\\unoptimized-image.mjs", "source_location": "L5"}, {"id": "scanners_unoptimized_image_scan", "label": "scan()", "file_type": "code", "source_file": "C:\\Users\\Diego Ramirez\\J-RNWConstructionSite\\.agents\\skills\\vercel-optimize\\lib\\scanners\\unoptimized-image.mjs", "source_location": "L28"}, {"id": "scanners_unoptimized_image_isjsxlike", "label": "isJsxLike()", "file_type": "code", "source_file": "C:\\Users\\Diego Ramirez\\J-RNWConstructionSite\\.agents\\skills\\vercel-optimize\\lib\\scanners\\unoptimized-image.mjs", "source_location": "L103"}, {"id": "scanners_unoptimized_image_isnextconfig", "label": "isNextConfig()", "file_type": "code", "source_file": "C:\\Users\\Diego Ramirez\\J-RNWConstructionSite\\.agents\\skills\\vercel-optimize\\lib\\scanners\\unoptimized-image.mjs", "source_location": "L106"}, {"id": "scanners_unoptimized_image_snippet", "label": "snippet()", "file_type": "code", "source_file": "C:\\Users\\Diego Ramirez\\J-RNWConstructionSite\\.agents\\skills\\vercel-optimize\\lib\\scanners\\unoptimized-image.mjs", "source_location": "L109"}], "edges": [{"source": "c_users_diego_ramirez_j_rnwconstructionsite_agents_skills_vercel_optimize_lib_scanners_unoptimized_image_mjs", "target": "scanners_unoptimized_image_metadata", "relation": "contains", "confidence": "EXTRACTED", "source_file": "C:\\Users\\Diego Ramirez\\J-RNWConstructionSite\\.agents\\skills\\vercel-optimize\\lib\\scanners\\unoptimized-image.mjs", "source_location": "L5", "weight": 1.0}, {"source": "c_users_diego_ramirez_j_rnwconstructionsite_agents_skills_vercel_optimize_lib_scanners_unoptimized_image_mjs", "target": "scanners_unoptimized_image_scan", "relation": "contains", "confidence": "EXTRACTED", "source_file": "C:\\Users\\Diego Ramirez\\J-RNWConstructionSite\\.agents\\skills\\vercel-optimize\\lib\\scanners\\unoptimized-image.mjs", "source_location": "L28", "weight": 1.0}, {"source": "c_users_diego_ramirez_j_rnwconstructionsite_agents_skills_vercel_optimize_lib_scanners_unoptimized_image_mjs", "target": "c_users_diego_ramirez_j_rnwconstructionsite_agents_skills_vercel_optimize_lib_util_mjs", "relation": "imports_from", "context": "import", "confidence": "EXTRACTED", "source_file": "C:\\Users\\Diego Ramirez\\J-RNWConstructionSite\\.agents\\skills\\vercel-optimize\\lib\\scanners\\unoptimized-image.mjs", "source_location": "L101", "weight": 1.0}, {"source": "c_users_diego_ramirez_j_rnwconstructionsite_agents_skills_vercel_optimize_lib_scanners_unoptimized_image_mjs", "target": "lib_util_lineof", "relation": "imports", "context": "import", "confidence": "EXTRACTED", "source_file": "C:\\Users\\Diego Ramirez\\J-RNWConstructionSite\\.agents\\skills\\vercel-optimize\\lib\\scanners\\unoptimized-image.mjs", "source_location": "L101", "weight": 1.0}, {"source": "c_users_diego_ramirez_j_rnwconstructionsite_agents_skills_vercel_optimize_lib_scanners_unoptimized_image_mjs", "target": "scanners_unoptimized_image_isjsxlike", "relation": "contains", "confidence": "EXTRACTED", "source_file": "C:\\Users\\Diego Ramirez\\J-RNWConstructionSite\\.agents\\skills\\vercel-optimize\\lib\\scanners\\unoptimized-image.mjs", "source_location": "L103", "weight": 1.0}, {"source": "c_users_diego_ramirez_j_rnwconstructionsite_agents_skills_vercel_optimize_lib_scanners_unoptimized_image_mjs", "target": "scanners_unoptimized_image_isnextconfig", "relation": "contains", "confidence": "EXTRACTED", "source_file": "C:\\Users\\Diego Ramirez\\J-RNWConstructionSite\\.agents\\skills\\vercel-optimize\\lib\\scanners\\unoptimized-image.mjs", "source_location": "L106", "weight": 1.0}, {"source": "c_users_diego_ramirez_j_rnwconstructionsite_agents_skills_vercel_optimize_lib_scanners_unoptimized_image_mjs", "target": "scanners_unoptimized_image_snippet", "relation": "contains", "confidence": "EXTRACTED", "source_file": "C:\\Users\\Diego Ramirez\\J-RNWConstructionSite\\.agents\\skills\\vercel-optimize\\lib\\scanners\\unoptimized-image.mjs", "source_location": "L109", "weight": 1.0}, {"source": "scanners_unoptimized_image_scan", "target": "scanners_unoptimized_image_isjsxlike", "relation": "calls", "context": "call", "confidence": "EXTRACTED", "source_file": "C:\\Users\\Diego Ramirez\\J-RNWConstructionSite\\.agents\\skills\\vercel-optimize\\lib\\scanners\\unoptimized-image.mjs", "source_location": "L31", "weight": 1.0}, {"source": "scanners_unoptimized_image_scan", "target": "scanners_unoptimized_image_snippet", "relation": "calls", "context": "call", "confidence": "EXTRACTED", "source_file": "C:\\Users\\Diego Ramirez\\J-RNWConstructionSite\\.agents\\skills\\vercel-optimize\\lib\\scanners\\unoptimized-image.mjs", "source_location": "L40", "weight": 1.0}, {"source": "scanners_unoptimized_image_scan", "target": "scanners_unoptimized_image_isnextconfig", "relation": "calls", "context": "call", "confidence": "EXTRACTED", "source_file": "C:\\Users\\Diego Ramirez\\J-RNWConstructionSite\\.agents\\skills\\vercel-optimize\\lib\\scanners\\unoptimized-image.mjs", "source_location": "L46", "weight": 1.0}], "raw_calls": [{"caller_nid": "scanners_unoptimized_image_scan", "callee": "exec", "is_member_call": true, "source_file": "C:\\Users\\Diego Ramirez\\J-RNWConstructionSite\\.agents\\skills\\vercel-optimize\\lib\\scanners\\unoptimized-image.mjs", "source_location": "L34"}, {"caller_nid": "scanners_unoptimized_image_scan", "callee": "push", "is_member_call": true, "source_file": "C:\\Users\\Diego Ramirez\\J-RNWConstructionSite\\.agents\\skills\\vercel-optimize\\lib\\scanners\\unoptimized-image.mjs", "source_location": "L35"}, {"caller_nid": "scanners_unoptimized_image_scan", "callee": "lineOf", "is_member_call": false, "source_file": "C:\\Users\\Diego Ramirez\\J-RNWConstructionSite\\.agents\\skills\\vercel-optimize\\lib\\scanners\\unoptimized-image.mjs", "source_location": "L39"}, {"caller_nid": "scanners_unoptimized_image_scan", "callee": "exec", "is_member_call": true, "source_file": "C:\\Users\\Diego Ramirez\\J-RNWConstructionSite\\.agents\\skills\\vercel-optimize\\lib\\scanners\\unoptimized-image.mjs", "source_location": "L47"}, {"caller_nid": "scanners_unoptimized_image_scan", "callee": "push", "is_member_call": true, "source_file": "C:\\Users\\Diego Ramirez\\J-RNWConstructionSite\\.agents\\skills\\vercel-optimize\\lib\\scanners\\unoptimized-image.mjs", "source_location": "L49"}, {"caller_nid": "scanners_unoptimized_image_scan", "callee": "lineOf", "is_member_call": false, "source_file": "C:\\Users\\Diego Ramirez\\J-RNWConstructionSite\\.agents\\skills\\vercel-optimize\\lib\\scanners\\unoptimized-image.mjs", "source_location": "L53"}, {"caller_nid": "scanners_unoptimized_image_scan", "callee": "test", "is_member_call": true, "source_file": "C:\\Users\\Diego Ramirez\\J-RNWConstructionSite\\.agents\\skills\\vercel-optimize\\lib\\scanners\\unoptimized-image.mjs", "source_location": "L63"}, {"caller_nid": "scanners_unoptimized_image_scan", "callee": "exec", "is_member_call": true, "source_file": "C:\\Users\\Diego Ramirez\\J-RNWConstructionSite\\.agents\\skills\\vercel-optimize\\lib\\scanners\\unoptimized-image.mjs", "source_location": "L66"}, {"caller_nid": "scanners_unoptimized_image_scan", "callee": "test", "is_member_call": true, "source_file": "C:\\Users\\Diego Ramirez\\J-RNWConstructionSite\\.agents\\skills\\vercel-optimize\\lib\\scanners\\unoptimized-image.mjs", "source_location": "L68"}, {"caller_nid": "scanners_unoptimized_image_scan", "callee": "test", "is_member_call": true, "source_file": "C:\\Users\\Diego Ramirez\\J-RNWConstructionSite\\.agents\\skills\\vercel-optimize\\lib\\scanners\\unoptimized-image.mjs", "source_location": "L69"}, {"caller_nid": "scanners_unoptimized_image_scan", "callee": "push", "is_member_call": true, "source_file": "C:\\Users\\Diego Ramirez\\J-RNWConstructionSite\\.agents\\skills\\vercel-optimize\\lib\\scanners\\unoptimized-image.mjs", "source_location": "L71"}, {"caller_nid": "scanners_unoptimized_image_scan", "callee": "lineOf", "is_member_call": false, "source_file": "C:\\Users\\Diego Ramirez\\J-RNWConstructionSite\\.agents\\skills\\vercel-optimize\\lib\\scanners\\unoptimized-image.mjs", "source_location": "L75"}, {"caller_nid": "scanners_unoptimized_image_scan", "callee": "slice", "is_member_call": true, "source_file": "C:\\Users\\Diego Ramirez\\J-RNWConstructionSite\\.agents\\skills\\vercel-optimize\\lib\\scanners\\unoptimized-image.mjs", "source_location": "L76"}, {"caller_nid": "scanners_unoptimized_image_scan", "callee": "exec", "is_member_call": true, "source_file": "C:\\Users\\Diego Ramirez\\J-RNWConstructionSite\\.agents\\skills\\vercel-optimize\\lib\\scanners\\unoptimized-image.mjs", "source_location": "L81"}, {"caller_nid": "scanners_unoptimized_image_scan", "callee": "test", "is_member_call": true, "source_file": "C:\\Users\\Diego Ramirez\\J-RNWConstructionSite\\.agents\\skills\\vercel-optimize\\lib\\scanners\\unoptimized-image.mjs", "source_location": "L84"}, {"caller_nid": "scanners_unoptimized_image_scan", "callee": "startsWith", "is_member_call": true, "source_file": "C:\\Users\\Diego Ramirez\\J-RNWConstructionSite\\.agents\\skills\\vercel-optimize\\lib\\scanners\\unoptimized-image.mjs", "source_location": "L84"}, {"caller_nid": "scanners_unoptimized_image_scan", "callee": "test", "is_member_call": true, "source_file": "C:\\Users\\Diego Ramirez\\J-RNWConstructionSite\\.agents\\skills\\vercel-optimize\\lib\\scanners\\unoptimized-image.mjs", "source_location": "L84"}, {"caller_nid": "scanners_unoptimized_image_scan", "callee": "push", "is_member_call": true, "source_file": "C:\\Users\\Diego Ramirez\\J-RNWConstructionSite\\.agents\\skills\\vercel-optimize\\lib\\scanners\\unoptimized-image.mjs", "source_location": "L85"}, {"caller_nid": "scanners_unoptimized_image_scan", "callee": "lineOf", "is_member_call": false, "source_file": "C:\\Users\\Diego Ramirez\\J-RNWConstructionSite\\.agents\\skills\\vercel-optimize\\lib\\scanners\\unoptimized-image.mjs", "source_location": "L89"}, {"caller_nid": "scanners_unoptimized_image_scan", "callee": "slice", "is_member_call": true, "source_file": "C:\\Users\\Diego Ramirez\\J-RNWConstructionSite\\.agents\\skills\\vercel-optimize\\lib\\scanners\\unoptimized-image.mjs", "source_location": "L90"}, {"caller_nid": "scanners_unoptimized_image_isjsxlike", "callee": "test", "is_member_call": true, "source_file": "C:\\Users\\Diego Ramirez\\J-RNWConstructionSite\\.agents\\skills\\vercel-optimize\\lib\\scanners\\unoptimized-image.mjs", "source_location": "L104"}, {"caller_nid": "scanners_unoptimized_image_isnextconfig", "callee": "test", "is_member_call": true, "source_file": "C:\\Users\\Diego Ramirez\\J-RNWConstructionSite\\.agents\\skills\\vercel-optimize\\lib\\scanners\\unoptimized-image.mjs", "source_location": "L107"}, {"caller_nid": "scanners_unoptimized_image_snippet", "callee": "lastIndexOf", "is_member_call": true, "source_file": "C:\\Users\\Diego Ramirez\\J-RNWConstructionSite\\.agents\\skills\\vercel-optimize\\lib\\scanners\\unoptimized-image.mjs", "source_location": "L110"}, {"caller_nid": "scanners_unoptimized_image_snippet", "callee": "indexOf", "is_member_call": true, "source_file": "C:\\Users\\Diego Ramirez\\J-RNWConstructionSite\\.agents\\skills\\vercel-optimize\\lib\\scanners\\unoptimized-image.mjs", "source_location": "L111"}, {"caller_nid": "scanners_unoptimized_image_snippet", "callee": "slice", "is_member_call": true, "source_file": "C:\\Users\\Diego Ramirez\\J-RNWConstructionSite\\.agents\\skills\\vercel-optimize\\lib\\scanners\\unoptimized-image.mjs", "source_location": "L112"}, {"caller_nid": "scanners_unoptimized_image_snippet", "callee": "trim", "is_member_call": true, "source_file": "C:\\Users\\Diego Ramirez\\J-RNWConstructionSite\\.agents\\skills\\vercel-optimize\\lib\\scanners\\unoptimized-image.mjs", "source_location": "L112"}, {"caller_nid": "scanners_unoptimized_image_snippet", "callee": "slice", "is_member_call": true, "source_file": "C:\\Users\\Diego Ramirez\\J-RNWConstructionSite\\.agents\\skills\\vercel-optimize\\lib\\scanners\\unoptimized-image.mjs", "source_location": "L112"}]}