{"nodes": [{"id": "c_users_diego_ramirez_j_rnwconstructionsite_lib_db_js", "label": "db.js", "file_type": "code", "source_file": "C:\\Users\\Diego Ramirez\\J-RNWConstructionSite\\lib\\db.js", "source_location": "L1"}, {"id": "lib_db_createdb", "label": "createDb()", "file_type": "code", "source_file": "C:\\Users\\Diego Ramirez\\J-RNWConstructionSite\\lib\\db.js", "source_location": "L6"}, {"id": "lib_db_getdb", "label": "getDb()", "file_type": "code", "source_file": "C:\\Users\\Diego Ramirez\\J-RNWConstructionSite\\lib\\db.js", "source_location": "L30"}], "edges": [{"source": "c_users_diego_ramirez_j_rnwconstructionsite_lib_db_js", "target": "client", "relation": "imports_from", "context": "import", "confidence": "EXTRACTED", "source_file": "C:\\Users\\Diego Ramirez\\J-RNWConstructionSite\\lib\\db.js", "source_location": "L1", "weight": 1.0}, {"source": "c_users_diego_ramirez_j_rnwconstructionsite_lib_db_js", "target": "lib_db_createdb", "relation": "contains", "confidence": "EXTRACTED", "source_file": "C:\\Users\\Diego Ramirez\\J-RNWConstructionSite\\lib\\db.js", "source_location": "L6", "weight": 1.0}, {"source": "c_users_diego_ramirez_j_rnwconstructionsite_lib_db_js", "target": "lib_db_getdb", "relation": "contains", "confidence": "EXTRACTED", "source_file": "C:\\Users\\Diego Ramirez\\J-RNWConstructionSite\\lib\\db.js", "source_location": "L30", "weight": 1.0}, {"source": "lib_db_getdb", "target": "lib_db_createdb", "relation": "calls", "context": "call", "confidence": "EXTRACTED", "source_file": "C:\\Users\\Diego Ramirez\\J-RNWConstructionSite\\lib\\db.js", "source_location": "L33", "weight": 1.0}], "raw_calls": [{"caller_nid": "lib_db_createdb", "callee": "createClient", "is_member_call": false, "source_file": "C:\\Users\\Diego Ramirez\\J-RNWConstructionSite\\lib\\db.js", "source_location": "L11"}, {"caller_nid": "lib_db_createdb", "callee": "createClient", "is_member_call": false, "source_file": "C:\\Users\\Diego Ramirez\\J-RNWConstructionSite\\lib\\db.js", "source_location": "L13"}]}