{"nodes": [{"id": "c_users_diego_ramirez_j_rnwconstructionsite_context_languagecontext_js", "label": "LanguageContext.js", "file_type": "code", "source_file": "C:\\Users\\Diego Ramirez\\J-RNWConstructionSite\\context\\LanguageContext.js", "source_location": "L1"}, {"id": "context_languagecontext_translations", "label": "translations", "file_type": "code", "source_file": "C:\\Users\\Diego Ramirez\\J-RNWConstructionSite\\context\\LanguageContext.js", "source_location": "L3"}, {"id": "context_languagecontext_languagecontext", "label": "LanguageContext", "file_type": "code", "source_file": "C:\\Users\\Diego Ramirez\\J-RNWConstructionSite\\context\\LanguageContext.js", "source_location": "L335"}, {"id": "context_languagecontext_languageprovider", "label": "LanguageProvider()", "file_type": "code", "source_file": "C:\\Users\\Diego Ramirez\\J-RNWConstructionSite\\context\\LanguageContext.js", "source_location": "L337"}, {"id": "context_languagecontext_uselang", "label": "useLang()", "file_type": "code", "source_file": "C:\\Users\\Diego Ramirez\\J-RNWConstructionSite\\context\\LanguageContext.js", "source_location": "L364"}], "edges": [{"source": "c_users_diego_ramirez_j_rnwconstructionsite_context_languagecontext_js", "target": "react", "relation": "imports_from", "context": "import", "confidence": "EXTRACTED", "source_file": "C:\\Users\\Diego Ramirez\\J-RNWConstructionSite\\context\\LanguageContext.js", "source_location": "L1", "weight": 1.0}, {"source": "c_users_diego_ramirez_j_rnwconstructionsite_context_languagecontext_js", "target": "context_languagecontext_translations", "relation": "contains", "confidence": "EXTRACTED", "source_file": "C:\\Users\\Diego Ramirez\\J-RNWConstructionSite\\context\\LanguageContext.js", "source_location": "L3", "weight": 1.0}, {"source": "c_users_diego_ramirez_j_rnwconstructionsite_context_languagecontext_js", "target": "context_languagecontext_languagecontext", "relation": "contains", "confidence": "EXTRACTED", "source_file": "C:\\Users\\Diego Ramirez\\J-RNWConstructionSite\\context\\LanguageContext.js", "source_location": "L335", "weight": 1.0}, {"source": "c_users_diego_ramirez_j_rnwconstructionsite_context_languagecontext_js", "target": "context_languagecontext_languageprovider", "relation": "contains", "confidence": "EXTRACTED", "source_file": "C:\\Users\\Diego Ramirez\\J-RNWConstructionSite\\context\\LanguageContext.js", "source_location": "L337", "weight": 1.0}, {"source": "c_users_diego_ramirez_j_rnwconstructionsite_context_languagecontext_js", "target": "context_languagecontext_uselang", "relation": "contains", "confidence": "EXTRACTED", "source_file": "C:\\Users\\Diego Ramirez\\J-RNWConstructionSite\\context\\LanguageContext.js", "source_location": "L364", "weight": 1.0}], "raw_calls": [{"caller_nid": "context_languagecontext_languageprovider", "callee": "useState", "is_member_call": false, "source_file": "C:\\Users\\Diego Ramirez\\J-RNWConstructionSite\\context\\LanguageContext.js", "source_location": "L338"}, {"caller_nid": "context_languagecontext_languageprovider", "callee": "useEffect", "is_member_call": false, "source_file": "C:\\Users\\Diego Ramirez\\J-RNWConstructionSite\\context\\LanguageContext.js", "source_location": "L340"}, {"caller_nid": "context_languagecontext_uselang", "callee": "useContext", "is_member_call": false, "source_file": "C:\\Users\\Diego Ramirez\\J-RNWConstructionSite\\context\\LanguageContext.js", "source_location": "L365"}]}